freetser/__init__.py
freetser/py.typed
freetser/server.py
freetser/storage.py
freetser-0.3.3.dist-info/WHEEL
freetser-0.3.3.dist-info/METADATA
freetser-0.3.3.dist-info/RECORD
