Metadata-Version: 2.3
Name: freetser
Version: 0.3.3
Summary: A free-threaded HTTP server built on top of h11
Author: Tip ten Brink
Author-email: Tip ten Brink <tip@tenbrinkmeijs.com>
Requires-Dist: h11>=0.16.0,<0.17.0
Requires-Python: >=3.14
